gblib/Config.cfg
gblib/__init__.py
gblib/__version__.py
gblib/gb_appsflyer.py
gblib/gb_bigquery.py
gblib/gb_common.py
gblib/gb_db.py
gblib/gb_file.py
gblib/gb_google.py
gblib/gb_hw.py
gblib/gb_log.py
gblib/gb_net.py
gblib/gb_sys.py
gblib/gb_threadpool.py
gblib/gb_time.py
tests/__init__.py
gblib-1.0.0.dist-info/LICENSE
gblib-1.0.0.dist-info/METADATA
gblib-1.0.0.dist-info/WHEEL
gblib-1.0.0.dist-info/top_level.txt
gblib-1.0.0.dist-info/RECORD
