Metadata-Version: 2.1
Name: gblib
Version: 1.0.0
Summary: UNKNOWN
Home-page: https://github.com/onefeng/gbutil
Author: onefeng
Author-email: 15198086902@163.com
License: MIT
Platform: UNKNOWN
Classifier: License :: OSI Approved :: MIT License
Classifier: Programming Language :: Python
Classifier: Programming Language :: Python :: 3
Classifier: Programming Language :: Python :: 3.6
Classifier: Programming Language :: Python :: Implementation :: CPython
Classifier: Programming Language :: Python :: Implementation :: PyPy
Requires-Python: >=3
License-File: LICENSE
Requires-Dist: PyMySQL (==0.10.1)
